dathost/__init__.py
dathost/base.py
dathost/exceptions.py
dathost/gamemodes.py
dathost/map_source.py
dathost/routes.py
dathost/settings.py
dathost/http/__init__.py
dathost/http/awaiting.py
dathost/http/base.py
dathost/http/blocking.py
dathost/match/__init__.py
dathost/match/awaiting.py
dathost/match/base.py
dathost/match/blocking.py
dathost/models/__init__.py
dathost/models/account.py
dathost/models/backup.py
dathost/models/file.py
dathost/models/match.py
dathost/models/metrics.py
dathost/models/server.py
dathost/server/__init__.py
dathost/server/base.py
dathost/server/awaiting/__init__.py
dathost/server/awaiting/backup.py
dathost/server/awaiting/file.py
dathost/server/blocking/__init__.py
dathost/server/blocking/backup.py
dathost/server/blocking/file.py
dathost/tests/__init__.py
dathost/tests/shared_vars.py
dathost/tests/test_awaiting.py
dathost/tests/test_blocking.py
dathost-1.0.2.dist-info/LICENSE
dathost-1.0.2.dist-info/METADATA
dathost-1.0.2.dist-info/WHEEL
dathost-1.0.2.dist-info/top_level.txt
dathost-1.0.2.dist-info/RECORD
