Metadata-Version: 2.1
Name: dathost
Version: 1.0.2
Summary: Asynchronous / Synchronous dathost API wrapper.
Home-page: https://dathost.readthedocs.io/en/latest/
Author: WardPearce
Author-email: wardpearce@protonmail.com
License: GPL v3
Platform: UNKNOWN
Requires-Python: >=3.6
License-File: LICENSE
Requires-Dist: httpx
Requires-Dist: asynctest
Requires-Dist: aiofiles
Requires-Dist: sphinxcontrib-trio
Requires-Dist: steam
Requires-Dist: sphinx-material
